stream_engine/__init__.py
stream_engine/stream.py
stream_engine-0.1.0.dist-info/METADATA
stream_engine-0.1.0.dist-info/RECORD
stream_engine-0.1.0.dist-info/WHEEL
stream_engine-0.1.0.dist-info/top_level.txt
