Metadata-Version: 2.1
Name: stream-engine
Version: 0.1.0
Summary: Matplotlib extension to plot real time data
Home-page: https://github.com/MA-MacDonald/stream-engine
Author: Michael MacDonald
Author-email: macdonald.michael.anthon@gmail.com
License: UNKNOWN
Platform: UNKNOWN
Classifier: Programming Language :: Python :: 3
Classifier: License :: OSI Approved :: MIT License
Classifier: Operating System :: OS Independent
Requires-Dist: matplotlib (<=2.2.0,>=2.0)
